MockSZ/Backgrounds.py
MockSZ/Constants.py
MockSZ/Conversions.py
MockSZ/ElectronDistributions.py
MockSZ/Models.py
MockSZ/MultiProcess.py
MockSZ/MultiStats.py
MockSZ/SinglePointing.py
MockSZ/SingleStats.py
MockSZ/Utils.py
MockSZ/__init__.py
MockSZ-0.1.1.dist-info/LICENSE
MockSZ-0.1.1.dist-info/METADATA
MockSZ-0.1.1.dist-info/WHEEL
MockSZ-0.1.1.dist-info/top_level.txt
MockSZ-0.1.1.dist-info/RECORD
